{"name":"login","id":"org.example.TestLoginFailed:login","testCaseName":"org.example.TestLoginFailed","testSteps":[{"number":1,"description":"Login ","duration":11421,"startTime":"2024-05-24T09:01:07.617883300+03:00[Europe/Athens]","result":"SUCCESS","precondition":false,"level":0,"children":[{"number":2,"description":"Login failed: whiteblack, vvsss","duration":11421,"startTime":"2024-05-24T09:00:55.238185500+03:00[Europe/Athens]","screenshots":[{"screenshot":"e58c52b27df67285f897df56fe74e9e7d16f943b52f68ace42244b3694ad94bc.png","timeStamp":1716530466658}],"result":"SUCCESS","precondition":false,"level":1}]}],"userStory":{"id":"org.example.TestLoginFailed","storyName":"Test login failed","storyClassName":"org.example.TestLoginFailed","path":"org.example","type":"story"},"featureTag":{"name":"Example/Test login failed","type":"story","displayName":"Example/Test login failed"},"title":"Login","tags":[{"name":"Example/Test login failed","type":"story","displayName":"Example/Test login failed"}],"startTime":"2024-05-24T09:01:07.437874900+03:00[Europe/Athens]","duration":0,"isManualTestingUpToDate":false,"dataTable":{"headers":["username","password"],"rows":[{"values":["whiteblack","vvsss"],"result":"SUCCESS"}],"predefinedRows":false,"dataSetDescriptors":[{"startRow":0,"rowCount":0}]},"manual":false,"result":"SUCCESS"}